crazyflow/__init__.py
crazyflow/constants.py
crazyflow/exception.py
crazyflow/utils.py
crazyflow/control/__init__.py
crazyflow/control/control.py
crazyflow/envs/__init__.py
crazyflow/envs/drone_env.py
crazyflow/envs/figure_8_env.py
crazyflow/envs/landing_env.py
crazyflow/envs/norm_actions_wrapper.py
crazyflow/envs/reach_pos_env.py
crazyflow/envs/reach_vel_env.py
crazyflow/models/cf2/assets.xml
crazyflow/models/cf2/cf2.xml
crazyflow/models/cf2/scene.xml
crazyflow/models/cf2/assets/cf2_0.obj
crazyflow/models/cf2/assets/cf2_1.obj
crazyflow/models/cf2/assets/cf2_2.obj
crazyflow/models/cf2/assets/cf2_3.obj
crazyflow/models/cf2/assets/cf2_4.obj
crazyflow/models/cf2/assets/cf2_5.obj
crazyflow/models/cf2/assets/cf2_6.obj
crazyflow/randomize/__init__.py
crazyflow/randomize/randomize.py
crazyflow/sim/__init__.py
crazyflow/sim/integration.py
crazyflow/sim/physics.py
crazyflow/sim/sim.py
crazyflow/sim/structs.py
crazyflow/sim/symbolic.py
crazyflow/sim/visualize.py
crazyflow-0.0.2.dist-info/licenses/LICENSE
crazyflow-0.0.2.dist-info/METADATA
crazyflow-0.0.2.dist-info/WHEEL
crazyflow-0.0.2.dist-info/top_level.txt
crazyflow-0.0.2.dist-info/RECORD
