Metadata-Version: 2.4
Name: crazyflow
Version: 0.0.2
Summary: Fast, parallelizable simulations of Crazyflies with JAX and MuJoCo.
License: The MIT License (MIT)
Project-URL: Homepage, https://github.com/utiasDSL/crazyflow
Project-URL: Repository, https://github.com/utiasDSL/crazyflow
Classifier: License :: OSI Approved :: MIT License
Classifier: Programming Language :: Python
Classifier: Programming Language :: Python :: 3
Classifier: Intended Audience :: Developers
Classifier: Intended Audience :: Education
Classifier: Intended Audience :: Science/Research
Requires-Python: >=3.11
License-File: LICENSE
Requires-Dist: jax>=0.7.0
Requires-Dist: mujoco>=3.3.0
Requires-Dist: mujoco-mjx>=3.3.0
Requires-Dist: gymnasium[mujoco]>=1.2.0
Requires-Dist: imageio
Requires-Dist: einops
Requires-Dist: flax
Requires-Dist: ml_collections
Requires-Dist: casadi
Requires-Dist: numpy
Provides-Extra: test
Requires-Dist: pytest>=8.0.0; extra == "test"
Requires-Dist: pytest-cov; extra == "test"
Requires-Dist: pytest-timeout; extra == "test"
Requires-Dist: gymnasium[array-api]; extra == "test"
Provides-Extra: gpu
Requires-Dist: jax[cuda12]; extra == "gpu"
Provides-Extra: benchmark
Requires-Dist: fire; extra == "benchmark"
Requires-Dist: matplotlib; extra == "benchmark"
Requires-Dist: pandas; extra == "benchmark"
Dynamic: license-file
